README.md
setup.cfg
setup.py
tweet_helper.py
tweet_helper.egg-info/PKG-INFO
tweet_helper.egg-info/SOURCES.txt
tweet_helper.egg-info/dependency_links.txt
tweet_helper.egg-info/entry_points.txt
tweet_helper.egg-info/not-zip-safe
tweet_helper.egg-info/requires.txt
tweet_helper.egg-info/top_level.txt