Metadata-Version: 1.1
Name: tweet-helper
Version: 0.0.3
Summary: twython wrapper to simplify tweeting from the commandline
Home-page: https://github.com/jvanasco/tweet_helper
Author: Jonathan Vanasco
Author-email: jonathan@findmeon.com
License: MIT
Platform: UNKNOWN
Classifier: Programming Language :: Python :: 2.7
Classifier: Programming Language :: Python :: 3
Classifier: Intended Audience :: Developers
